LICENSE
MANIFEST.in
README.rst
setup.py
testkit/__init__.py
testkit/context.py
testkit/data.py
testkit/directory.py
testkit/exceptionutils.py
testkit/processes.py
testkit/shunt.py
testkit/timeouts.py
testkit/utils.py
testkit.egg-info/PKG-INFO
testkit.egg-info/SOURCES.txt
testkit.egg-info/dependency_links.txt
testkit.egg-info/not-zip-safe
testkit.egg-info/requires.txt
testkit.egg-info/top_level.txt