Metadata-Version: 1.1
Name: testkit
Version: 0.1.7
Summary: testkit - A collection of tools for testing
Home-page: https://github.com/ravenac95/testkit
Author: Reuven V. Gonzales
Author-email: reuven@tobetter.us
License: MIT
Platform: Unix
Classifier: License :: OSI Approved :: MIT License
Classifier: Intended Audience :: Developers
Classifier: Programming Language :: Python
Classifier: Operating System :: POSIX
